aldryn_forms_recaptcha_plugin/__init__.py
aldryn_forms_recaptcha_plugin/cms_plugins.py
aldryn_forms_recaptcha_plugin/templates/snowpenguin/recaptcha/recaptcha_hidden_input.html
aldryn_forms_recaptcha_plugin-1.0.0.2.dist-info/LICENSE
aldryn_forms_recaptcha_plugin-1.0.0.2.dist-info/METADATA
aldryn_forms_recaptcha_plugin-1.0.0.2.dist-info/WHEEL
aldryn_forms_recaptcha_plugin-1.0.0.2.dist-info/top_level.txt
aldryn_forms_recaptcha_plugin-1.0.0.2.dist-info/RECORD
