Metadata-Version: 2.1
Name: aldryn-forms-recaptcha-plugin
Version: 1.0.0.2
Summary: A simple invisible recaptcha v3 implementation
Home-page: https://gitlab.com/what-digital/aldryn-forms-recaptcha-plugin/
Author: what.digital
Author-email: mario@what.digital
License: UNKNOWN
Platform: OS Independent
Requires-Dist: aldryn-forms (>=5.0.3)
Requires-Dist: django-recaptcha3 (>=0.2.0)
